rlgraph/__init__.py
rlgraph/version.py
rlgraph/agents/__init__.py
rlgraph/agents/actor_critic_agent.py
rlgraph/agents/agent.py
rlgraph/agents/apex_agent.py
rlgraph/agents/dqfd_agent.py
rlgraph/agents/dqn_agent.py
rlgraph/agents/impala_agents.py
rlgraph/agents/ppo_agent.py
rlgraph/agents/random_agent.py
rlgraph/agents/sac_agent.py
rlgraph/components/__init__.py
rlgraph/components/component.py
rlgraph/components/action_adapters/__init__.py
rlgraph/components/action_adapters/action_adapter.py
rlgraph/components/action_adapters/action_adapter_utils.py
rlgraph/components/action_adapters/bernoulli_distribution_adapter.py
rlgraph/components/action_adapters/beta_distribution_adapter.py
rlgraph/components/action_adapters/categorical_distribution_adapter.py
rlgraph/components/action_adapters/gumbel_softmax_distribution_adapter.py
rlgraph/components/action_adapters/normal_distribution_adapter.py
rlgraph/components/action_adapters/squashed_normal_distribution_adapter.py
rlgraph/components/common/__init__.py
rlgraph/components/common/batch_apply.py
rlgraph/components/common/batch_splitter.py
rlgraph/components/common/container_merger.py
rlgraph/components/common/decay_components.py
rlgraph/components/common/environment_stepper.py
rlgraph/components/common/iterative_optimization.py
rlgraph/components/common/multi_gpu_synchronizer.py
rlgraph/components/common/noise_components.py
rlgraph/components/common/repeater_stack.py
rlgraph/components/common/sampler.py
rlgraph/components/common/slice.py
rlgraph/components/common/softmax.py
rlgraph/components/common/staging_area.py
rlgraph/components/common/synchronizable.py
rlgraph/components/common/time_dependent_parameters.py
rlgraph/components/distributions/__init__.py
rlgraph/components/distributions/bernoulli.py
rlgraph/components/distributions/beta.py
rlgraph/components/distributions/categorical.py
rlgraph/components/distributions/distribution.py
rlgraph/components/distributions/gumbel_softmax.py
rlgraph-0.5.2.dist-info/LICENSE
rlgraph-0.5.2.dist-info/METADATA
rlgraph-0.5.2.dist-info/WHEEL
rlgraph-0.5.2.dist-info/top_level.txt
rlgraph-0.5.2.dist-info/RECORD
